gym_causalenv/__init__.py
gym_causalenv/envs/__init__.py
gym_causalenv/envs/causal_env.py
gym_causalenv-0.1.0.dist-info/WHEEL
gym_causalenv-0.1.0.dist-info/METADATA
gym_causalenv-0.1.0.dist-info/RECORD
