Metadata-Version: 2.1
Name: gym-causalenv
Version: 0.1.0
Summary: 
Author: Elias Aoun Durand
Author-email: elias.aoundurand@gmail.com
Requires-Python: >=3.8,<4.0
Classifier: Programming Language :: Python :: 3
Classifier: Programming Language :: Python :: 3.8
Classifier: Programming Language :: Python :: 3.9
Requires-Dist: gym (>=0.0,<0.1)
